{
  "task": "Build the Redis rate limiter",
  "current_stage": "codegen",
  "iteration": 0,
  "results": [
    {
      "agent": "architect",
      "status": "failed",
      "duration": 12.260244369506836,
      "retries": 1
    },
    {
      "agent": "architect",
      "status": "completed",
      "duration": 52.83213973045349,
      "retries": 0
    },
    {
      "agent": "codegen",
      "status": "failed",
      "duration": 180.013929605484,
      "retries": 1
    },
    {
      "agent": "codegen",
      "status": "failed",
      "duration": 180.00833106040955,
      "retries": 2
    },
    {
      "agent": "codegen",
      "status": "failed",
      "duration": 2.275618076324463,
      "retries": 3
    },
    {
      "agent": "codegen",
      "status": "failed",
      "duration": 180.00806379318237,
      "retries": 4
    },
    {
      "agent": "codegen",
      "status": "failed",
      "duration": 180.01325821876526,
      "retries": 5
    }
  ]
}